zezfio
zezfio/io
zezfio/lib
zezfio/template
