Metadata-Version: 1.1
Name: zezfio
Version: 0.9.5
Summary: The lovely client/server version of Ezfio
Home-page: https://github.com/TApplencourt/Zezfio2
Author: Thomas applencourt
Author-email: applencourt@irsamc.ups-tlse.fr
License: UNKNOWN
Download-URL: https://github.com/TApplencourt/Zezfio2/archive/master.zip
Keywords: programming,fortran,EZFIO,ZMQ
Platform: UNKNOWN
